{
  "id": "57f9a1a4-bd52-4aed-9fbd-12b174afb773",
  "prevId": "fd29d9cd-1ed2-4d62-8447-cfbdbdd1d700",
  "version": "7",
  "dialect": "postgresql",
  "tables": {
    "public.articles": {
      "name": "articles",
      "schema": "",
      "columns": {
        "id": {
          "name": "id",
          "type": "uuid",
          "primaryKey": true,
          "notNull": true,
          "default": "gen_random_uuid()"
        },
        "event_id": {
          "name": "event_id",
          "type": "uuid",
          "primaryKey": false,
          "notNull": false
        },
        "sport_id": {
          "name": "sport_id",
          "type": "uuid",
          "primaryKey": false,
          "notNull": true
        },
        "title": {
          "name": "title",
          "type": "text",
          "primaryKey": false,
          "notNull": true
        },
        "summary": {
          "name": "summary",
          "type": "text",
          "primaryKey": false,
          "notNull": false
        },
        "content": {
          "name": "content",
          "type": "text",
          "primaryKey": false,
          "notNull": true
        },
        "tone": {
          "name": "tone",
          "type": "article_tone",
          "typeSchema": "public",
          "primaryKey": false,
          "notNull": true,
          "default": "'neutral'"
        },
        "language": {
          "name": "language",
          "type": "article_language",
          "typeSchema": "public",
          "primaryKey": false,
          "notNull": true,
          "default": "'fr'"
        },
        "status": {
          "name": "status",
          "type": "article_status",
          "typeSchema": "public",
          "primaryKey": false,
          "notNull": true,
          "default": "'pending'"
        },
        "sources": {
          "name": "sources",
          "type": "text[]",
          "primaryKey": false,
          "notNull": true,
          "default": "ARRAY[]::text[]"
        },
        "generated_at": {
          "name": "generated_at",
          "type": "timestamp",
          "primaryKey": false,
          "notNull": false
        },
        "created_at": {
          "name": "created_at",
          "type": "timestamp",
          "primaryKey": false,
          "notNull": true,
          "default": "now()"
        },
        "deleted_at": {
          "name": "deleted_at",
          "type": "timestamp",
          "primaryKey": false,
          "notNull": false
        },
        "search_vector": {
          "name": "search_vector",
          "type": "tsvector",
          "primaryKey": false,
          "notNull": false,
          "generated": {
            "as": "to_tsvector('french', coalesce(title, '') || ' ' || coalesce(content, ''))",
            "type": "stored"
          }
        }
      },
      "indexes": {
        "articles_sport_id_idx": {
          "name": "articles_sport_id_idx",
          "columns": [
            {
              "expression": "sport_id",
              "isExpression": false,
              "asc": true,
              "nulls": "last"
            }
          ],
          "isUnique": false,
          "concurrently": false,
          "method": "btree",
          "with": {}
        },
        "articles_status_idx": {
          "name": "articles_status_idx",
          "columns": [
            {
              "expression": "status",
              "isExpression": false,
              "asc": true,
              "nulls": "last"
            }
          ],
          "isUnique": false,
          "concurrently": false,
          "method": "btree",
          "with": {}
        },
        "articles_language_idx": {
          "name": "articles_language_idx",
          "columns": [
            {
              "expression": "language",
              "isExpression": false,
              "asc": true,
              "nulls": "last"
            }
          ],
          "isUnique": false,
          "concurrently": false,
          "method": "btree",
          "with": {}
        },
        "articles_created_at_idx": {
          "name": "articles_created_at_idx",
          "columns": [
            {
              "expression": "created_at",
              "isExpression": false,
              "asc": true,
              "nulls": "last"
            }
          ],
          "isUnique": false,
          "concurrently": false,
          "method": "btree",
          "with": {}
        },
        "articles_search_vector_gin_idx": {
          "name": "articles_search_vector_gin_idx",
          "columns": [
            {
              "expression": "\"search_vector\"",
              "asc": true,
              "isExpression": true,
              "nulls": "last"
            }
          ],
          "isUnique": false,
          "concurrently": false,
          "method": "gin",
          "with": {}
        }
      },
      "foreignKeys": {
        "articles_event_id_events_id_fk": {
          "name": "articles_event_id_events_id_fk",
          "tableFrom": "articles",
          "tableTo": "events",
          "columnsFrom": [
            "event_id"
          ],
          "columnsTo": [
            "id"
          ],
          "onDelete": "set null",
          "onUpdate": "no action"
        },
        "articles_sport_id_sports_id_fk": {
          "name": "articles_sport_id_sports_id_fk",
          "tableFrom": "articles",
          "tableTo": "sports",
          "columnsFrom": [
            "sport_id"
          ],
          "columnsTo": [
            "id"
          ],
          "onDelete": "cascade",
          "onUpdate": "no action"
        }
      },
      "compositePrimaryKeys": {},
      "uniqueConstraints": {},
      "policies": {},
      "checkConstraints": {},
      "isRLSEnabled": false
    },
    "public.events": {
      "name": "events",
      "schema": "",
      "columns": {
        "id": {
          "name": "id",
          "type": "uuid",
          "primaryKey": true,
          "notNull": true,
          "default": "gen_random_uuid()"
        },
        "external_id": {
          "name": "external_id",
          "type": "text",
          "primaryKey": false,
          "notNull": true
        },
        "sport_id": {
          "name": "sport_id",
          "type": "uuid",
          "primaryKey": false,
          "notNull": true
        },
        "home_team_id": {
          "name": "home_team_id",
          "type": "uuid",
          "primaryKey": false,
          "notNull": true
        },
        "away_team_id": {
          "name": "away_team_id",
          "type": "uuid",
          "primaryKey": false,
          "notNull": true
        },
        "home_score": {
          "name": "home_score",
          "type": "integer",
          "primaryKey": false,
          "notNull": false
        },
        "away_score": {
          "name": "away_score",
          "type": "integer",
          "primaryKey": false,
          "notNull": false
        },
        "venue": {
          "name": "venue",
          "type": "text",
          "primaryKey": false,
          "notNull": false
        },
        "competition": {
          "name": "competition",
          "type": "text",
          "primaryKey": false,
          "notNull": false
        },
        "status": {
          "name": "status",
          "type": "event_status",
          "typeSchema": "public",
          "primaryKey": false,
          "notNull": true
        },
        "started_at": {
          "name": "started_at",
          "type": "timestamp",
          "primaryKey": false,
          "notNull": true
        },
        "created_at": {
          "name": "created_at",
          "type": "timestamp",
          "primaryKey": false,
          "notNull": true,
          "default": "now()"
        }
      },
      "indexes": {
        "events_sport_id_idx": {
          "name": "events_sport_id_idx",
          "columns": [
            {
              "expression": "sport_id",
              "isExpression": false,
              "asc": true,
              "nulls": "last"
            }
          ],
          "isUnique": false,
          "concurrently": false,
          "method": "btree",
          "with": {}
        },
        "events_status_idx": {
          "name": "events_status_idx",
          "columns": [
            {
              "expression": "status",
              "isExpression": false,
              "asc": true,
              "nulls": "last"
            }
          ],
          "isUnique": false,
          "concurrently": false,
          "method": "btree",
          "with": {}
        },
        "events_started_at_idx": {
          "name": "events_started_at_idx",
          "columns": [
            {
              "expression": "started_at",
              "isExpression": false,
              "asc": true,
              "nulls": "last"
            }
          ],
          "isUnique": false,
          "concurrently": false,
          "method": "btree",
          "with": {}
        }
      },
      "foreignKeys": {
        "events_sport_id_sports_id_fk": {
          "name": "events_sport_id_sports_id_fk",
          "tableFrom": "events",
          "tableTo": "sports",
          "columnsFrom": [
            "sport_id"
          ],
          "columnsTo": [
            "id"
          ],
          "onDelete": "cascade",
          "onUpdate": "no action"
        },
        "events_home_team_id_teams_id_fk": {
          "name": "events_home_team_id_teams_id_fk",
          "tableFrom": "events",
          "tableTo": "teams",
          "columnsFrom": [
            "home_team_id"
          ],
          "columnsTo": [
            "id"
          ],
          "onDelete": "cascade",
          "onUpdate": "no action"
        },
        "events_away_team_id_teams_id_fk": {
          "name": "events_away_team_id_teams_id_fk",
          "tableFrom": "events",
          "tableTo": "teams",
          "columnsFrom": [
            "away_team_id"
          ],
          "columnsTo": [
            "id"
          ],
          "onDelete": "cascade",
          "onUpdate": "no action"
        }
      },
      "compositePrimaryKeys": {},
      "uniqueConstraints": {
        "events_external_id_unique": {
          "name": "events_external_id_unique",
          "nullsNotDistinct": false,
          "columns": [
            "external_id"
          ]
        }
      },
      "policies": {},
      "checkConstraints": {},
      "isRLSEnabled": false
    },
    "public.news_topics": {
      "name": "news_topics",
      "schema": "",
      "columns": {
        "id": {
          "name": "id",
          "type": "uuid",
          "primaryKey": true,
          "notNull": true,
          "default": "gen_random_uuid()"
        },
        "sport_id": {
          "name": "sport_id",
          "type": "uuid",
          "primaryKey": false,
          "notNull": true
        },
        "entities": {
          "name": "entities",
          "type": "text[]",
          "primaryKey": false,
          "notNull": true
        },
        "keywords": {
          "name": "keywords",
          "type": "text[]",
          "primaryKey": false,
          "notNull": true
        },
        "headline": {
          "name": "headline",
          "type": "text",
          "primaryKey": false,
          "notNull": true
        },
        "sources_count": {
          "name": "sources_count",
          "type": "integer",
          "primaryKey": false,
          "notNull": true
        },
        "score": {
          "name": "score",
          "type": "integer",
          "primaryKey": false,
          "notNull": true
        },
        "raw_excerpts": {
          "name": "raw_excerpts",
          "type": "jsonb",
          "primaryKey": false,
          "notNull": true
        },
        "article_id": {
          "name": "article_id",
          "type": "uuid",
          "primaryKey": false,
          "notNull": false
        },
        "first_seen_at": {
          "name": "first_seen_at",
          "type": "timestamp",
          "primaryKey": false,
          "notNull": true,
          "default": "now()"
        },
        "created_at": {
          "name": "created_at",
          "type": "timestamp",
          "primaryKey": false,
          "notNull": true,
          "default": "now()"
        }
      },
      "indexes": {
        "news_topics_sport_id_idx": {
          "name": "news_topics_sport_id_idx",
          "columns": [
            {
              "expression": "sport_id",
              "isExpression": false,
              "asc": true,
              "nulls": "last"
            }
          ],
          "isUnique": false,
          "concurrently": false,
          "method": "btree",
          "with": {}
        },
        "news_topics_score_idx": {
          "name": "news_topics_score_idx",
          "columns": [
            {
              "expression": "score",
              "isExpression": false,
              "asc": true,
              "nulls": "last"
            }
          ],
          "isUnique": false,
          "concurrently": false,
          "method": "btree",
          "with": {}
        },
        "news_topics_first_seen_at_idx": {
          "name": "news_topics_first_seen_at_idx",
          "columns": [
            {
              "expression": "first_seen_at",
              "isExpression": false,
              "asc": true,
              "nulls": "last"
            }
          ],
          "isUnique": false,
          "concurrently": false,
          "method": "btree",
          "with": {}
        },
        "news_topics_article_id_idx": {
          "name": "news_topics_article_id_idx",
          "columns": [
            {
              "expression": "article_id",
              "isExpression": false,
              "asc": true,
              "nulls": "last"
            }
          ],
          "isUnique": false,
          "concurrently": false,
          "method": "btree",
          "with": {}
        }
      },
      "foreignKeys": {
        "news_topics_sport_id_sports_id_fk": {
          "name": "news_topics_sport_id_sports_id_fk",
          "tableFrom": "news_topics",
          "tableTo": "sports",
          "columnsFrom": [
            "sport_id"
          ],
          "columnsTo": [
            "id"
          ],
          "onDelete": "cascade",
          "onUpdate": "no action"
        },
        "news_topics_article_id_articles_id_fk": {
          "name": "news_topics_article_id_articles_id_fk",
          "tableFrom": "news_topics",
          "tableTo": "articles",
          "columnsFrom": [
            "article_id"
          ],
          "columnsTo": [
            "id"
          ],
          "onDelete": "set null",
          "onUpdate": "no action"
        }
      },
      "compositePrimaryKeys": {},
      "uniqueConstraints": {},
      "policies": {},
      "checkConstraints": {},
      "isRLSEnabled": false
    },
    "public.sports": {
      "name": "sports",
      "schema": "",
      "columns": {
        "id": {
          "name": "id",
          "type": "uuid",
          "primaryKey": true,
          "notNull": true,
          "default": "gen_random_uuid()"
        },
        "name": {
          "name": "name",
          "type": "text",
          "primaryKey": false,
          "notNull": true
        },
        "slug": {
          "name": "slug",
          "type": "text",
          "primaryKey": false,
          "notNull": true
        },
        "created_at": {
          "name": "created_at",
          "type": "timestamp",
          "primaryKey": false,
          "notNull": true,
          "default": "now()"
        }
      },
      "indexes": {},
      "foreignKeys": {},
      "compositePrimaryKeys": {},
      "uniqueConstraints": {
        "sports_slug_unique": {
          "name": "sports_slug_unique",
          "nullsNotDistinct": false,
          "columns": [
            "slug"
          ]
        }
      },
      "policies": {},
      "checkConstraints": {},
      "isRLSEnabled": false
    },
    "public.teams": {
      "name": "teams",
      "schema": "",
      "columns": {
        "id": {
          "name": "id",
          "type": "uuid",
          "primaryKey": true,
          "notNull": true,
          "default": "gen_random_uuid()"
        },
        "external_id": {
          "name": "external_id",
          "type": "text",
          "primaryKey": false,
          "notNull": true
        },
        "name": {
          "name": "name",
          "type": "text",
          "primaryKey": false,
          "notNull": true
        },
        "short_name": {
          "name": "short_name",
          "type": "text",
          "primaryKey": false,
          "notNull": false
        },
        "logo_url": {
          "name": "logo_url",
          "type": "text",
          "primaryKey": false,
          "notNull": false
        },
        "sport_id": {
          "name": "sport_id",
          "type": "uuid",
          "primaryKey": false,
          "notNull": true
        },
        "country": {
          "name": "country",
          "type": "text",
          "primaryKey": false,
          "notNull": false
        },
        "created_at": {
          "name": "created_at",
          "type": "timestamp",
          "primaryKey": false,
          "notNull": true,
          "default": "now()"
        }
      },
      "indexes": {},
      "foreignKeys": {
        "teams_sport_id_sports_id_fk": {
          "name": "teams_sport_id_sports_id_fk",
          "tableFrom": "teams",
          "tableTo": "sports",
          "columnsFrom": [
            "sport_id"
          ],
          "columnsTo": [
            "id"
          ],
          "onDelete": "cascade",
          "onUpdate": "no action"
        }
      },
      "compositePrimaryKeys": {},
      "uniqueConstraints": {
        "teams_external_id_unique": {
          "name": "teams_external_id_unique",
          "nullsNotDistinct": false,
          "columns": [
            "external_id"
          ]
        }
      },
      "policies": {},
      "checkConstraints": {},
      "isRLSEnabled": false
    },
    "public.users": {
      "name": "users",
      "schema": "",
      "columns": {
        "id": {
          "name": "id",
          "type": "uuid",
          "primaryKey": true,
          "notNull": true,
          "default": "gen_random_uuid()"
        },
        "email": {
          "name": "email",
          "type": "text",
          "primaryKey": false,
          "notNull": true
        },
        "display_name": {
          "name": "display_name",
          "type": "text",
          "primaryKey": false,
          "notNull": false
        },
        "preferred_sports": {
          "name": "preferred_sports",
          "type": "text[]",
          "primaryKey": false,
          "notNull": true,
          "default": "ARRAY[]::text[]"
        },
        "preferred_language": {
          "name": "preferred_language",
          "type": "article_language",
          "typeSchema": "public",
          "primaryKey": false,
          "notNull": true,
          "default": "'fr'"
        },
        "created_at": {
          "name": "created_at",
          "type": "timestamp",
          "primaryKey": false,
          "notNull": true,
          "default": "now()"
        },
        "updated_at": {
          "name": "updated_at",
          "type": "timestamp",
          "primaryKey": false,
          "notNull": true,
          "default": "now()"
        }
      },
      "indexes": {},
      "foreignKeys": {},
      "compositePrimaryKeys": {},
      "uniqueConstraints": {
        "users_email_unique": {
          "name": "users_email_unique",
          "nullsNotDistinct": false,
          "columns": [
            "email"
          ]
        }
      },
      "policies": {},
      "checkConstraints": {},
      "isRLSEnabled": false
    }
  },
  "enums": {
    "public.article_language": {
      "name": "article_language",
      "schema": "public",
      "values": [
        "fr",
        "en"
      ]
    },
    "public.article_status": {
      "name": "article_status",
      "schema": "public",
      "values": [
        "pending",
        "generating",
        "published",
        "failed"
      ]
    },
    "public.article_tone": {
      "name": "article_tone",
      "schema": "public",
      "values": [
        "neutral",
        "analytical",
        "enthusiastic"
      ]
    },
    "public.event_status": {
      "name": "event_status",
      "schema": "public",
      "values": [
        "scheduled",
        "live",
        "finished",
        "cancelled"
      ]
    }
  },
  "schemas": {},
  "sequences": {},
  "roles": {},
  "policies": {},
  "views": {},
  "_meta": {
    "columns": {},
    "schemas": {},
    "tables": {}
  }
}